pypingcli/__init__.py
pypingcli/__main__.py
pypingcli/cli.py
pypingcli/util.py
pypingcli/commands/__init__.py
pypingcli/commands/base.py
pypingcli/commands/connectIP.py
pypingcli/commands/prompts.py
pypingcli/commands/setUser.py
pypingcli/commands/start.py
pypingcli/commands/stateManager.py
pypingcli/commands/util.py
pypingcli/cryptoManager/__init__.py
pypingcli/cryptoManager/aes.py
pypingcli/cryptoManager/keyManager.py
pypingcli/messaging/__init__.py
pypingcli/messaging/socketAction.py
pypingcli/sockets/__init__.py
pypingcli/sockets/client.py
pypingcli/sockets/server.py
pypingcli/sockets/util.py
pypingcli-0.1.dev1.dist-info/METADATA
pypingcli-0.1.dev1.dist-info/RECORD
pypingcli-0.1.dev1.dist-info/WHEEL
pypingcli-0.1.dev1.dist-info/entry_points.txt
pypingcli-0.1.dev1.dist-info/top_level.txt
