Metadata-Version: 2.1
Name: pypingcli
Version: 0.1.dev1
Summary: UNKNOWN
Home-page: https://github.com/tameeshB/pyPingCLI
Author: Tameesh Biswas
Author-email: g@tameesh.in
License: MIT
Keywords: cli
Platform: UNKNOWN
Classifier: Intended Audience :: End Users/Desktop
Classifier: Topic :: Utilities
Classifier: License :: OSI Approved :: MIT License
Classifier: Natural Language :: English
Classifier: Operating System :: OS Independent
Classifier: Programming Language :: Python :: 2
Classifier: Programming Language :: Python :: 2.6
Classifier: Programming Language :: Python :: 2.7
Classifier: Programming Language :: Python :: 3
Classifier: Programming Language :: Python :: 3.2
Classifier: Programming Language :: Python :: 3.3
Classifier: Programming Language :: Python :: 3.4
Provides-Extra: test
Requires-Dist: docopt
Requires-Dist: pycrypto
Provides-Extra: test
Requires-Dist: coverage; extra == 'test'
Requires-Dist: pytest; extra == 'test'
Requires-Dist: pytest-cov; extra == 'test'
